{
  "$schema": "../../schemas/model.json",
  "ambient_occlusion": false,
  "elements": [
    {
      "start": [0.4375, 0, 0.4375],
      "end": [0.5625, 0.0625, 0.5625],
      "faces": {
        "top": {
          "texture": "#main",
          "uv": [
            [8, 2],
            [10, 0]
          ]
        },
        "bottom": {
          "texture": "#main",
          "uv": [
            [8, 1],
            [10, 0]
          ]
        },
        "left": {
          "texture": "#main",
          "uv": [
            [8, 0],
            [8, 1]
          ]
        },
        "right": {
          "texture": "#main",
          "uv": [
            [10, 0],
            [8, 1]
          ]
        },
        "front": {
          "texture": "#main",
          "uv": [
            [10, 0],
            [9, 1]
          ]
        },
        "back": {
          "texture": "#main",
          "uv": [
            [9, 0],
            [8, 1]
          ]
        }
      }
    },
    {
      "start": [0.4375, 0.0625, 0.4375],
      "end": [0.5, 0.1875, 0.5],
      "faces": {
        "top": {
          "texture": "#main",
          "uv": [
            [8, 3],
            [9, 2]
          ]
        },
        "left": {
          "texture": "#main",
          "uv": [
            [9, 1],
            [8, 3]
          ]
        },
        "right": {
          "texture": "#main",
          "uv": [
            [9, 1],
            [8, 3]
          ]
        },
        "front": {
          "texture": "#main",
          "uv": [
            [9, 1],
            [8, 3]
          ]
        },
        "back": {
          "texture": "#main",
          "uv": [
            [9, 1],
            [8, 3]
          ]
        }
      }
    },
    {
      "start": [0.375, 0.1875, 0.375],
      "end": [0.4375, 0.3125, 0.4375],
      "faces": {
        "top": {
          "texture": "#main",
          "uv": [
            [7, 5],
            [8, 4]
          ]
        },
        "bottom": {
          "texture": "#main",
          "uv": [
            [7, 4],
            [8, 3]
          ]
        },
        "left": {
          "texture": "#main",
          "uv": [
            [8, 3],
            [7, 5]
          ]
        },
        "right": {
          "texture": "#main",
          "uv": [
            [8, 3],
            [7, 5]
          ]
        },
        "front": {
          "texture": "#main",
          "uv": [
            [8, 3],
            [7, 5]
          ]
        },
        "back": {
          "texture": "#main",
          "uv": [
            [8, 3],
            [7, 5]
          ]
        }
      }
    },
    {
      "start": [0.4375, 0.3125, 0.4375],
      "end": [0.5, 0.375, 0.5],
      "faces": {
        "bottom": {
          "texture": "#main",
          "uv": [
            [8, 6],
            [9, 5]
          ]
        },
        "left": {
          "texture": "#main",
          "uv": [
            [9, 5],
            [8, 6]
          ]
        },
        "right": {
          "texture": "#main",
          "uv": [
            [9, 5],
            [8, 6]
          ]
        },
        "front": {
          "texture": "#main",
          "uv": [
            [9, 5],
            [8, 6]
          ]
        },
        "back": {
          "texture": "#main",
          "uv": [
            [9, 5],
            [8, 6]
          ]
        }
      }
    },
    {
      "start": [0.4375, 0.375, 0.4375],
      "end": [0.5625, 0.4375, 0.5625],
      "rotation": {
        "origin": [0.5, 0.375, 0.5],
        "angle": 90,
        "axis": "y"
      },
      "faces": {
        "bottom": {
          "texture": "#main",
          "uv": [
            [7, 7],
            [9, 5]
          ]
        },
        "left": {
          "texture": "#main",
          "uv": [
            [9, 6],
            [7, 7]
          ]
        },
        "right": {
          "texture": "#main",
          "uv": [
            [9, 6],
            [7, 7]
          ]
        },
        "front": {
          "texture": "#main",
          "uv": [
            [9, 6],
            [7, 7]
          ]
        },
        "back": {
          "texture": "#main",
          "uv": [
            [9, 6],
            [7, 7]
          ]
        }
      }
    },
    {
      "start": [0.375, 0.4375, 0.375],
      "end": [0.625, 0.5, 0.625],
      "faces": {
        "top": {
          "texture": "#main",
          "uv": [
            [6, 11],
            [10, 7]
          ]
        },
        "bottom": {
          "texture": "#main",
          "uv": [
            [6, 11],
            [10, 7]
          ]
        },
        "left": {
          "texture": "#main",
          "uv": [
            [10, 10],
            [6, 11]
          ]
        },
        "right": {
          "texture": "#main",
          "uv": [
            [10, 10],
            [6, 11]
          ]
        },
        "front": {
          "texture": "#main",
          "uv": [
            [10, 7],
            [6, 8]
          ]
        },
        "back": {
          "texture": "#main",
          "uv": [
            [10, 7],
            [6, 8]
          ]
        }
      }
    },
    {
      "start": [0.4375, 0.5, 0.4375],
      "end": [0.5625, 0.5625, 0.5625],
      "faces": {
        "top": {
          "texture": "#main",
          "uv": [
            [7, 10],
            [9, 8]
          ]
        },
        "left": {
          "texture": "#main",
          "uv": [
            [7, 8],
            [9, 9]
          ]
        },
        "right": {
          "texture": "#main",
          "uv": [
            [9, 8],
            [7, 9]
          ]
        },
        "front": {
          "texture": "#main",
          "uv": [
            [7, 9],
            [9, 10]
          ]
        },
        "back": {
          "texture": "#main",
          "uv": [
            [9, 8],
            [7, 9]
          ]
        }
      }
    },
    {
      "start": [0.3125, 0.5, 0.375],
      "end": [0.375, 0.5625, 0.625],
      "faces": {
        "top": {
          "texture": "#main",
          "uv": [
            [10, 11],
            [11, 7]
          ]
        },
        "bottom": {
          "texture": "#main",
          "uv": [
            [10, 11],
            [11, 7]
          ]
        },
        "left": {
          "texture": "#main",
          "uv": [
            [12, 10],
            [8, 11]
          ]
        },
        "right": {
          "texture": "#main",
          "uv": [
            [12, 10],
            [8, 11]
          ]
        },
        "front": {
          "texture": "#main",
          "uv": [
            [11, 10],
            [10, 11]
          ]
        },
        "back": {
          "texture": "#main",
          "uv": [
            [11, 10],
            [10, 11]
          ]
        }
      }
    },
    {
      "start": [0.625, 0.5, 0.375],
      "end": [0.6875, 0.5625, 0.625],
      "faces": {
        "top": {
          "texture": "#main",
          "uv": [
            [6, 11],
            [7, 7]
          ]
        },
        "bottom": {
          "texture": "#main",
          "uv": [
            [7, 11],
            [8, 7]
          ]
        },
        "left": {
          "texture": "#main",
          "uv": [
            [6, 7],
            [10, 8]
          ]
        },
        "right": {
          "texture": "#main",
          "uv": [
            [10, 10],
            [6, 11]
          ]
        },
        "front": {
          "texture": "#main",
          "uv": [
            [7, 10],
            [6, 11]
          ]
        },
        "back": {
          "texture": "#main",
          "uv": [
            [7, 7],
            [6, 8]
          ]
        }
      }
    },
    {
      "start": [0.375, 0.5, 0.3125],
      "end": [0.625, 0.5625, 0.375],
      "faces": {
        "top": {
          "texture": "#main",
          "uv": [
            [7, 8],
            [11, 7]
          ]
        },
        "bottom": {
          "texture": "#main",
          "uv": [
            [7, 11],
            [11, 10]
          ]
        },
        "left": {
          "texture": "#main",
          "uv": [
            [11, 7],
            [10, 8]
          ]
        },
        "right": {
          "texture": "#main",
          "uv": [
            [11, 10],
            [10, 11]
          ]
        },
        "front": {
          "texture": "#main",
          "uv": [
            [11, 10],
            [7, 11]
          ]
        },
        "back": {
          "texture": "#main",
          "uv": [
            [11, 7],
            [7, 8]
          ]
        }
      }
    },
    {
      "start": [0.375, 0.5, 0.625],
      "end": [0.625, 0.5625, 0.6875],
      "faces": {
        "top": {
          "texture": "#main",
          "uv": [
            [6, 11],
            [10, 10]
          ]
        },
        "bottom": {
          "texture": "#main",
          "uv": [
            [8, 11],
            [12, 10]
          ]
        },
        "left": {
          "texture": "#main",
          "uv": [
            [7, 10],
            [6, 11]
          ]
        },
        "right": {
          "texture": "#main",
          "uv": [
            [11, 10],
            [10, 11]
          ]
        },
        "front": {
          "texture": "#main",
          "uv": [
            [10, 10],
            [6, 11]
          ]
        },
        "back": {
          "texture": "#main",
          "uv": [
            [9, 10],
            [5, 11]
          ]
        }
      }
    },
    {
      "start": [0.6875, 0.5, 0.5625],
      "end": [0.75, 0.5625, 0.625],
      "faces": {
        "top": {
          "texture": "#main",
          "uv": [
            [8, 13],
            [9, 12]
          ]
        },
        "bottom": {
          "texture": "#main",
          "uv": [
            [8, 13],
            [9, 12]
          ]
        },
        "left": {
          "texture": "#main",
          "uv": [
            [9, 12],
            [8, 13]
          ]
        },
        "right": {
          "texture": "#main",
          "uv": [
            [9, 12],
            [8, 13]
          ]
        },
        "front": {
          "texture": "#main",
          "uv": [
            [9, 12],
            [8, 13]
          ]
        },
        "back": {
          "texture": "#main",
          "uv": [
            [9, 12],
            [8, 13]
          ]
        }
      }
    },
    {
      "start": [0.25, 0.5, 0.375],
      "end": [0.3125, 0.5625, 0.4375],
      "faces": {
        "top": {
          "texture": "#main",
          "uv": [
            [11, 9],
            [12, 8]
          ]
        },
        "bottom": {
          "texture": "#main",
          "uv": [
            [11, 9],
            [12, 8]
          ]
        },
        "left": {
          "texture": "#main",
          "uv": [
            [12, 8],
            [11, 9]
          ]
        },
        "right": {
          "texture": "#main",
          "uv": [
            [12, 8],
            [11, 9]
          ]
        },
        "front": {
          "texture": "#main",
          "uv": [
            [12, 8],
            [11, 9]
          ]
        },
        "back": {
          "texture": "#main",
          "uv": [
            [12, 8],
            [11, 9]
          ]
        }
      }
    },
    {
      "start": [0.25, 0.5, 0.5],
      "end": [0.3125, 0.5625, 0.5625],
      "faces": {
        "top": {
          "texture": "#main",
          "uv": [
            [11, 11],
            [12, 10]
          ]
        },
        "bottom": {
          "texture": "#main",
          "uv": [
            [11, 11],
            [12, 10]
          ]
        },
        "left": {
          "texture": "#main",
          "uv": [
            [12, 10],
            [11, 11]
          ]
        },
        "right": {
          "texture": "#main",
          "uv": [
            [12, 10],
            [11, 11]
          ]
        },
        "front": {
          "texture": "#main",
          "uv": [
            [12, 10],
            [11, 11]
          ]
        },
        "back": {
          "texture": "#main",
          "uv": [
            [12, 10],
            [11, 11]
          ]
        }
      }
    },
    {
      "start": [0.5, 0.5, 0.25],
      "end": [0.5625, 0.5625, 0.3125],
      "faces": {
        "top": {
          "texture": "#main",
          "uv": [
            [6, 7],
            [7, 6]
          ]
        },
        "bottom": {
          "texture": "#main",
          "uv": [
            [6, 7],
            [7, 6]
          ]
        },
        "left": {
          "texture": "#main",
          "uv": [
            [7, 6],
            [6, 7]
          ]
        },
        "right": {
          "texture": "#main",
          "uv": [
            [7, 6],
            [6, 7]
          ]
        },
        "front": {
          "texture": "#main",
          "uv": [
            [7, 6],
            [6, 7]
          ]
        },
        "back": {
          "texture": "#main",
          "uv": [
            [7, 6],
            [6, 7]
          ]
        }
      }
    },
    {
      "start": [0.4375, 0.5, 0.6875],
      "end": [0.5, 0.5625, 0.75],
      "faces": {
        "top": {
          "texture": "#main",
          "uv": [
            [4, 10],
            [5, 9]
          ]
        },
        "bottom": {
          "texture": "#main",
          "uv": [
            [4, 10],
            [5, 9]
          ]
        },
        "left": {
          "texture": "#main",
          "uv": [
            [5, 9],
            [4, 10]
          ]
        },
        "right": {
          "texture": "#main",
          "uv": [
            [5, 9],
            [4, 10]
          ]
        },
        "front": {
          "texture": "#main",
          "uv": [
            [5, 9],
            [4, 10]
          ]
        },
        "back": {
          "texture": "#main",
          "uv": [
            [5, 9],
            [4, 10]
          ]
        }
      }
    }
  ]
}
